cram_archiver/__init__.py
cram_archiver/__main__.py
cram_archiver/_version.py
cram_archiver/_version.pyi
cram_archiver/references.py
cram_archiver-1.1.0.dist-info/licenses/LICENSE
cram_archiver-1.1.0.dist-info/METADATA
cram_archiver-1.1.0.dist-info/WHEEL
cram_archiver-1.1.0.dist-info/entry_points.txt
cram_archiver-1.1.0.dist-info/top_level.txt
cram_archiver-1.1.0.dist-info/RECORD
