Metadata-Version: 2.4
Name: cram-archiver
Version: 1.1.0
Summary: A samtools wrapper for CRAM conversion automation.
Author-email: Leiden University Medical Center <sasc@lumc.nl>
License-Expression: AGPL-3.0-or-later
Project-URL: Homepage, https://github.com/lumc/cram-archiver
Keywords: CRAM,archive
Classifier: Programming Language :: Python :: 3 :: Only
Classifier: Programming Language :: Python :: 3
Classifier: Programming Language :: Python :: 3.10
Classifier: Programming Language :: Python :: 3.11
Classifier: Programming Language :: Python :: 3.12
Classifier: Programming Language :: Python :: 3.13
Classifier: Development Status :: 5 - Production/Stable
Classifier: Topic :: Scientific/Engineering :: Bio-Informatics
Requires-Python: >=3.10
License-File: LICENSE
Dynamic: license-file
